test.py
stadb/__init__.py
stadb/logger.py
stadb/postgresql.py
stadb/sensorthings.py
stadb/timescaledb.py
stadb/utils.py
stadb-0.0.6.dist-info/LICENSE
stadb-0.0.6.dist-info/METADATA
stadb-0.0.6.dist-info/WHEEL
stadb-0.0.6.dist-info/top_level.txt
stadb-0.0.6.dist-info/RECORD
