Metadata-Version: 2.1
Name: stadb
Version: 0.0.6
Summary: SensorThings API database connector for advanced functionalities
Author-email: Enoc Martínez <enoc.martinez@upc.edu>
Maintainer-email: Enoc Martínez <enoc.martinez@upc.edu>
License: MIT License
Project-URL: Homepage, https://github.com/EnocMartinez/stadb
Project-URL: Source, https://github.com/EnocMartinez/stadb
Keywords: sta,setuptools,development,sensorthings
Classifier: Development Status :: 3 - Alpha
Classifier: Intended Audience :: Developers
Classifier: Topic :: Software Development :: Build Tools
Classifier: License :: OSI Approved :: MIT License
Classifier: Programming Language :: Python :: 3
Classifier: Programming Language :: Python :: 3.8
Classifier: Programming Language :: Python :: 3.9
Classifier: Programming Language :: Python :: 3.10
Classifier: Programming Language :: Python :: 3.11
Classifier: Programming Language :: Python :: 3.12
Classifier: Programming Language :: Python :: 3 :: Only
Requires-Python: >=3.8
License-File: LICENSE
Requires-Dist: rich >=12.5.1
Requires-Dist: pandas >=1.4.3
Requires-Dist: psycopg2-binary >=2.9.1
